emptool/__init__.py
emptool/common.py
py_emptool_common-0.0.7.dist-info/LICENSE
py_emptool_common-0.0.7.dist-info/METADATA
py_emptool_common-0.0.7.dist-info/WHEEL
py_emptool_common-0.0.7.dist-info/top_level.txt
py_emptool_common-0.0.7.dist-info/RECORD
